<?xml version="1.0" encoding="UTF-8"?>
<!DOCTYPE list SYSTEM "npc.dtd">
<list>
	<npc id="4301" name="Queen of Hearts" title="Valentine Messenger">
		<set name="type" value="Npc"/>
		<set name="ai_type" value="NpcAI"/>
		<set name="collision_height" value="15"/>
		<set name="collision_radius" value="8"/>
		<set name="level" value="70"/>
		<set name="rewardExp" value="0"/>
		<set name="rewardRp" value="0"/>
		<set name="rewardSp" value="10"/>
		<set name="baseHpMax" value="2444.46819"/>
		<set name="baseHpRate" value="1"/>
		<set name="baseHpReg" value="7.5"/>
		<set name="baseMpMax" value="1345.8"/>
		<set name="baseMpReg" value="2.7"/>
		<set name="baseSTR" value="40"/>
		<set name="baseCON" value="43"/>
		<set name="baseDEX" value="30"/>
		<set name="baseINT" value="21"/>
		<set name="baseMEN" value="20"/>
		<set name="baseWIT" value="20"/>
		<set name="basePCritRate" value="40"/>
		<set name="basePAtk" value="688.86373"/>
		<set name="basePDef" value="295.91597"/>
		<set name="basePAtkSpd" value="253"/>
		<set name="baseMAtk" value="470.40463"/>
		<set name="baseMDef" value="216.53847"/>
		<set name="baseWalkSpd" value="26"/>
		<set name="baseRunSpd" value="120"/>
		<set name="baseShldDef" value="0"/>
		<set name="baseShldRate" value="0"/>
		<set name="baseAtkRange" value="40"/>
		<set name="baseRandDam" value="30"/>
		<set name="baseAttackType" value="SWORD"/>
		<set name="basePHitModify" value="4.75"/>
		<set name="basePAvoidModify" value="0"/>
		<set name="baseHitTimeFactor" value="0.48"/>
		<set name="baseReuseDelay" value="0"/>
		<set name="baseSafeHeight" value="100"/>
		<set name="aggroRange" value="0"/>
		<set name="shots" value="NONE"/>
		<set name="texture" value=""/>
		<set name="baseDamageRange" value="0;0;80;120"/>
		<skills>
			<skill id="4416" level="7"/>	<!--Spirits-->
			<skill id="4408" level="1"/>	<!--HP Increase (1x)-->
			<skill id="4409" level="1"/>	<!--MP Increase (1x)-->
			<skill id="4410" level="11"/>	<!--Average P. Atk.-->
			<skill id="4411" level="11"/>	<!--Average M. Atk.-->
			<skill id="4412" level="11"/>	<!--Average P. Def.-->
			<skill id="4413" level="11"/>	<!--Average M. Def.-->
			<skill id="4414" level="2"/>	<!--Standard Type-->
			<skill id="4415" level="3"/>	<!--One-handed Sword-->
			<skill id="4045" level="1"/>	<!--Resist Full Magic Attack-->
		</skills>
	</npc>
	<npc id="4302" name="Master Dugi" title="Soul Healer">
		<set name="type" value="Npc"/>
		<set name="ai_type" value="NpcAI"/>
		<set name="collision_height" value="16.7"/>
		<set name="collision_radius" value="9"/>
		<set name="level" value="1"/>
		<set name="rewardExp" value="0"/>
		<set name="rewardRp" value="0"/>
		<set name="rewardSp" value="0"/>
		<set name="baseHpMax" value="39.74519"/>
		<set name="baseHpRate" value="1"/>
		<set name="baseHpReg" value="2"/>
		<set name="baseMpMax" value="40"/>
		<set name="baseMpReg" value="0.9"/>
		<set name="baseSTR" value="40"/>
		<set name="baseCON" value="43"/>
		<set name="baseDEX" value="30"/>
		<set name="baseINT" value="21"/>
		<set name="baseMEN" value="20"/>
		<set name="baseWIT" value="20"/>
		<set name="basePCritRate" value="40"/>
		<set name="basePAtk" value="8.47458"/>
		<set name="basePDef" value="44.44444"/>
		<set name="basePAtkSpd" value="253"/>
		<set name="baseMAtk" value="5.78704"/>
		<set name="baseMDef" value="32.52252"/>
		<set name="baseWalkSpd" value="50"/>
		<set name="baseRunSpd" value="160"/>
		<set name="baseShldDef" value="0"/>
		<set name="baseShldRate" value="0"/>
		<set name="baseAtkRange" value="40"/>
		<set name="baseRandDam" value="10"/>
		<set name="baseAttackType" value="FIST"/>
		<set name="basePHitModify" value="4.75"/>
		<set name="basePAvoidModify" value="0"/>
		<set name="baseHitTimeFactor" value="0.6"/>
		<set name="baseReuseDelay" value="0"/>
		<set name="baseSafeHeight" value="100"/>
		<set name="aggroRange" value="0"/>
		<set name="shots" value="NONE"/>
		<set name="texture" value=""/>
		<set name="baseDamageRange" value="0;0;80;120"/>
		<skills>
			<skill id="4416" level="6"/>	<!--Humanoids-->
			<skill id="4408" level="1"/>	<!--HP Increase (1x)-->
			<skill id="4409" level="1"/>	<!--MP Increase (1x)-->
			<skill id="4410" level="11"/>	<!--Average P. Atk.-->
			<skill id="4411" level="11"/>	<!--Average M. Atk.-->
			<skill id="4412" level="11"/>	<!--Average P. Def.-->
			<skill id="4413" level="11"/>	<!--Average M. Def.-->
			<skill id="4414" level="2"/>	<!--Standard Type-->
			<skill id="4415" level="1"/>	<!--Bare Hands-->
			<skill id="4045" level="1"/>	<!--Resist Full Magic Attack-->
		</skills>
	</npc>
	<npc id="4303" name="Skooldy" title="Halloween Children">
		<set name="type" value="Npc"/>
		<set name="ai_type" value="NpcAI"/>
		<set name="collision_height" value="16"/>
		<set name="collision_radius" value="10"/>
		<set name="level" value="85"/>
		<set name="rewardExp" value="722"/>
		<set name="rewardRp" value="0"/>
		<set name="rewardSp" value="10"/>
		<set name="baseHpMax" value="2444.46819"/>
		<set name="baseHpRate" value="1"/>
		<set name="baseHpReg" value="7.5"/>
		<set name="baseMpMax" value="1345.8"/>
		<set name="baseMpReg" value="2.7"/>
		<set name="baseSTR" value="40"/>
		<set name="baseCON" value="43"/>
		<set name="baseDEX" value="30"/>
		<set name="baseINT" value="21"/>
		<set name="baseMEN" value="20"/>
		<set name="baseWIT" value="20"/>
		<set name="basePCritRate" value="40"/>
		<set name="basePAtk" value="688.86373"/>
		<set name="basePDef" value="295.91597"/>
		<set name="basePAtkSpd" value="253"/>
		<set name="baseMAtk" value="470.40463"/>
		<set name="baseMDef" value="216.53847"/>
		<set name="baseWalkSpd" value="50"/>
		<set name="baseRunSpd" value="120"/>
		<set name="baseShldDef" value="0"/>
		<set name="baseShldRate" value="0"/>
		<set name="baseAtkRange" value="40"/>
		<set name="baseRandDam" value="30"/>
		<set name="baseAttackType" value="SWORD"/>
		<set name="basePHitModify" value="4.75"/>
		<set name="basePAvoidModify" value="0"/>
		<set name="baseHitTimeFactor" value="0.6"/>
		<set name="baseReuseDelay" value="0"/>
		<set name="baseSafeHeight" value="100"/>
		<set name="aggroRange" value="0"/>
		<set name="shots" value="NONE"/>
		<set name="texture" value=""/>
		<set name="baseDamageRange" value="0;0;80;120"/>
		<skills>
			<skill id="4416" level="4"/>	<!--Animals-->
			<skill id="4408" level="1"/>	<!--HP Increase (1x)-->
			<skill id="4409" level="1"/>	<!--MP Increase (1x)-->
			<skill id="4410" level="11"/>	<!--Average P. Atk.-->
			<skill id="4411" level="11"/>	<!--Average M. Atk.-->
			<skill id="4412" level="11"/>	<!--Average P. Def.-->
			<skill id="4413" level="11"/>	<!--Average M. Def.-->
			<skill id="4414" level="2"/>	<!--Standard Type-->
			<skill id="4415" level="5"/>	<!--Blunt Weapons-->
			<skill id="4390" level="1"/>	<!--NPC Abnormal Immunity-->
		</skills>
	</npc>
	<npc id="4304" name="White-Bearded Santa" title="Merry Christmas~">
		<set name="type" value="Npc"/>
		<set name="ai_type" value="NpcAI"/>
		<set name="collision_height" value="24"/>
		<set name="collision_radius" value="8"/>
		<set name="level" value="70"/>
		<set name="rewardExp" value="490"/>
		<set name="rewardRp" value="0"/>
		<set name="rewardSp" value="10"/>
		<set name="baseHpMax" value="2444.46819"/>
		<set name="baseHpRate" value="1"/>
		<set name="baseHpReg" value="7.5"/>
		<set name="baseMpMax" value="1345.8"/>
		<set name="baseMpReg" value="2.7"/>
		<set name="baseSTR" value="40"/>
		<set name="baseCON" value="43"/>
		<set name="baseDEX" value="30"/>
		<set name="baseINT" value="21"/>
		<set name="baseMEN" value="20"/>
		<set name="baseWIT" value="20"/>
		<set name="basePCritRate" value="40"/>
		<set name="basePAtk" value="688.86373"/>
		<set name="basePDef" value="295.91597"/>
		<set name="basePAtkSpd" value="253"/>
		<set name="baseMAtk" value="470.40463"/>
		<set name="baseMDef" value="216.53847"/>
		<set name="baseWalkSpd" value="50"/>
		<set name="baseRunSpd" value="120"/>
		<set name="baseShldDef" value="0"/>
		<set name="baseShldRate" value="0"/>
		<set name="baseAtkRange" value="40"/>
		<set name="baseRandDam" value="30"/>
		<set name="baseAttackType" value="SWORD"/>
		<set name="basePHitModify" value="4.75"/>
		<set name="basePAvoidModify" value="0"/>
		<set name="baseHitTimeFactor" value="0.6"/>
		<set name="baseReuseDelay" value="0"/>
		<set name="baseSafeHeight" value="100"/>
		<set name="aggroRange" value="0"/>
		<set name="shots" value="NONE"/>
		<set name="texture" value=""/>
		<set name="baseDamageRange" value="0;0;80;120"/>
		<skills>
			<skill id="4416" level="18"/>	<!--Dwarves-->
			<skill id="4408" level="1"/>	<!--HP Increase (1x)-->
			<skill id="4409" level="1"/>	<!--MP Increase (1x)-->
			<skill id="4410" level="11"/>	<!--Average P. Atk.-->
			<skill id="4411" level="11"/>	<!--Average M. Atk.-->
			<skill id="4412" level="11"/>	<!--Average P. Def.-->
			<skill id="4413" level="11"/>	<!--Average M. Def.-->
			<skill id="4414" level="2"/>	<!--Standard Type-->
			<skill id="4415" level="3"/>	<!--One-handed Sword-->
			<skill id="4045" level="1"/>	<!--Resist Full Magic Attack-->
		</skills>
	</npc>
	<npc id="4305" name="Rosalia" title="Helpless Romantic">
		<set name="type" value="Npc"/>
		<set name="ai_type" value="NpcAI"/>
		<set name="collision_height" value="20"/>
		<set name="collision_radius" value="10"/>
		<set name="level" value="70"/>
		<set name="rewardExp" value="0"/>
		<set name="rewardRp" value="0"/>
		<set name="rewardSp" value="0"/>
		<set name="baseHpMax" value="2444.46819"/>
		<set name="baseHpRate" value="1"/>
		<set name="baseHpReg" value="7.5"/>
		<set name="baseMpMax" value="1345.8"/>
		<set name="baseMpReg" value="2.7"/>
		<set name="baseSTR" value="40"/>
		<set name="baseCON" value="43"/>
		<set name="baseDEX" value="30"/>
		<set name="baseINT" value="21"/>
		<set name="baseMEN" value="20"/>
		<set name="baseWIT" value="20"/>
		<set name="basePCritRate" value="40"/>
		<set name="basePAtk" value="688.86373"/>
		<set name="basePDef" value="295.91597"/>
		<set name="basePAtkSpd" value="253"/>
		<set name="baseMAtk" value="470.40463"/>
		<set name="baseMDef" value="216.53847"/>
		<set name="baseWalkSpd" value="50"/>
		<set name="baseRunSpd" value="160"/>
		<set name="baseShldDef" value="0"/>
		<set name="baseShldRate" value="0"/>
		<set name="baseAtkRange" value="40"/>
		<set name="baseRandDam" value="10"/>
		<set name="baseAttackType" value="FIST"/>
		<set name="basePHitModify" value="5"/>
		<set name="basePAvoidModify" value="0"/>
		<set name="baseHitTimeFactor" value="0.6"/>
		<set name="baseReuseDelay" value="0"/>
		<set name="baseSafeHeight" value="100"/>
		<set name="aggroRange" value="0"/>
		<set name="shots" value="NONE"/>
		<set name="texture" value=""/>
		<set name="baseDamageRange" value="0;0;80;120"/>
		<skills>
			<skill id="4416" level="14"/>	<!--Humans-->
			<skill id="4408" level="1"/>	<!--HP Increase (1x)-->
			<skill id="4409" level="1"/>	<!--MP Increase (1x)-->
			<skill id="4410" level="11"/>	<!--Average P. Atk.-->
			<skill id="4411" level="11"/>	<!--Average M. Atk.-->
			<skill id="4412" level="11"/>	<!--Average P. Def.-->
			<skill id="4413" level="11"/>	<!--Average M. Def.-->
			<skill id="4414" level="2"/>	<!--Standard Type-->
			<skill id="4415" level="1"/>	<!--Bare Hands-->
			<skill id="4045" level="1"/>	<!--Resist Full Magic Attack-->
		</skills>
	</npc>
	<npc id="4306" name="Steve Shyagel" title="Eva's High Priest">
		<set name="type" value="Npc"/>
		<set name="ai_type" value="NpcAI"/>
		<set name="collision_height" value="26.5"/>
		<set name="collision_radius" value="8"/>
		<set name="level" value="85"/>
		<set name="rewardExp" value="722"/>
		<set name="rewardRp" value="0"/>
		<set name="rewardSp" value="10"/>
		<set name="baseHpMax" value="2444.46819"/>
		<set name="baseHpRate" value="1"/>
		<set name="baseHpReg" value="7.5"/>
		<set name="baseMpMax" value="1345.8"/>
		<set name="baseMpReg" value="2.7"/>
		<set name="baseSTR" value="40"/>
		<set name="baseCON" value="43"/>
		<set name="baseDEX" value="30"/>
		<set name="baseINT" value="21"/>
		<set name="baseMEN" value="20"/>
		<set name="baseWIT" value="20"/>
		<set name="basePCritRate" value="40"/>
		<set name="basePAtk" value="688.86373"/>
		<set name="basePDef" value="295.91597"/>
		<set name="basePAtkSpd" value="253"/>
		<set name="baseMAtk" value="470.40463"/>
		<set name="baseMDef" value="216.53847"/>
		<set name="baseWalkSpd" value="50"/>
		<set name="baseRunSpd" value="120"/>
		<set name="baseShldDef" value="0"/>
		<set name="baseShldRate" value="0"/>
		<set name="baseAtkRange" value="40"/>
		<set name="baseRandDam" value="30"/>
		<set name="baseAttackType" value="SWORD"/>
		<set name="basePHitModify" value="4.75"/>
		<set name="basePAvoidModify" value="0"/>
		<set name="baseHitTimeFactor" value="0.6"/>
		<set name="baseReuseDelay" value="0"/>
		<set name="baseSafeHeight" value="100"/>
		<set name="aggroRange" value="0"/>
		<set name="shots" value="NONE"/>
		<set name="texture" value=""/>
		<set name="baseDamageRange" value="0;0;80;120"/>
		<skills>
			<skill id="4416" level="14"/>	<!--Humans-->
			<skill id="4408" level="1"/>	<!--HP Increase (1x)-->
			<skill id="4409" level="1"/>	<!--MP Increase (1x)-->
			<skill id="4410" level="11"/>	<!--Average P. Atk.-->
			<skill id="4411" level="11"/>	<!--Average M. Atk.-->
			<skill id="4412" level="11"/>	<!--Average P. Def.-->
			<skill id="4413" level="11"/>	<!--Average M. Def.-->
			<skill id="4414" level="2"/>	<!--Standard Type-->
			<skill id="4415" level="3"/>	<!--One-handed Sword-->
			<skill id="4045" level="1"/>	<!--Resist Full Magic Attack-->
		</skills>
	</npc>
	<npc id="4307" name="Santa Claus" title="Event Manager">
		<set name="type" value="Npc"/>
		<set name="ai_type" value="NpcAI"/>
		<set name="collision_height" value="25"/>
		<set name="collision_radius" value="12"/>
		<set name="level" value="80"/>
		<set name="rewardExp" value="0"/>
		<set name="rewardRp" value="0"/>
		<set name="rewardSp" value="0"/>
		<set name="baseHpMax" value="3290.11306877694"/>
		<set name="baseHpRate" value="1"/>
		<set name="baseHpReg" value="8.5"/>
		<set name="baseMpMax" value="1674.8"/>
		<set name="baseMpReg" value="3"/>
		<set name="baseSTR" value="40"/>
		<set name="baseCON" value="43"/>
		<set name="baseDEX" value="30"/>
		<set name="baseINT" value="21"/>
		<set name="baseMEN" value="20"/>
		<set name="baseWIT" value="20"/>
		<set name="basePCritRate" value="40"/>
		<set name="basePAtk" value="970.537548504614"/>
		<set name="basePDef" value="341.375"/>
		<set name="basePAtkSpd" value="253"/>
		<set name="baseMAtk" value="662.751329129412"/>
		<set name="baseMDef" value="249.80341"/>
		<set name="baseWalkSpd" value="50"/>
		<set name="baseRunSpd" value="120"/>
		<set name="baseShldDef" value="0"/>
		<set name="baseShldRate" value="0"/>
		<set name="baseAtkRange" value="40"/>
		<set name="baseRandDam" value="10"/>
		<set name="baseAttackType" value="FIST"/>
		<set name="basePHitModify" value="5"/>
		<set name="basePAvoidModify" value="0"/>
		<set name="baseHitTimeFactor" value="0.6"/>
		<set name="baseReuseDelay" value="0"/>
		<set name="baseSafeHeight" value="100"/>
		<set name="aggroRange" value="0"/>
		<set name="shots" value="NONE"/>
		<set name="texture" value=""/>
		<set name="baseDamageRange" value="0;0;80;120"/>
		<skills>
			<skill id="4416" level="14"/>	<!--Humans-->
			<skill id="4408" level="1"/>	<!--HP Increase (1x)-->
			<skill id="4409" level="1"/>	<!--MP Increase (1x)-->
			<skill id="4410" level="11"/>	<!--Average P. Atk.-->
			<skill id="4411" level="11"/>	<!--Average M. Atk.-->
			<skill id="4412" level="11"/>	<!--Average P. Def.-->
			<skill id="4413" level="11"/>	<!--Average M. Def.-->
			<skill id="4414" level="2"/>	<!--Standard Type-->
			<skill id="4415" level="1"/>	<!--Bare Hands-->
			<skill id="4390" level="1"/>	<!--NPC Abnormal Immunity-->
			<skill id="4045" level="1"/>	<!--Resist Full Magic Attack-->
		</skills>
	</npc>
	<npc id="4308" name="Angel Cat" title="Love's Envoy">
		<set name="type" value="Npc"/>
		<set name="ai_type" value="NpcAI"/>
		<set name="collision_height" value="16"/>
		<set name="collision_radius" value="6"/>
		<set name="level" value="70"/>
		<set name="rewardExp" value="0"/>
		<set name="rewardRp" value="0"/>
		<set name="rewardSp" value="0"/>
		<set name="baseHpMax" value="2444.46819"/>
		<set name="baseHpRate" value="1"/>
		<set name="baseHpReg" value="7.5"/>
		<set name="baseMpMax" value="1345.8"/>
		<set name="baseMpReg" value="2.7"/>
		<set name="baseSTR" value="40"/>
		<set name="baseCON" value="43"/>
		<set name="baseDEX" value="30"/>
		<set name="baseINT" value="21"/>
		<set name="baseMEN" value="20"/>
		<set name="baseWIT" value="20"/>
		<set name="basePCritRate" value="40"/>
		<set name="basePAtk" value="688.86373"/>
		<set name="basePDef" value="295.91597"/>
		<set name="basePAtkSpd" value="253"/>
		<set name="baseMAtk" value="470.40463"/>
		<set name="baseMDef" value="216.53847"/>
		<set name="baseWalkSpd" value="48"/>
		<set name="baseRunSpd" value="140"/>
		<set name="baseShldDef" value="0"/>
		<set name="baseShldRate" value="0"/>
		<set name="baseAtkRange" value="40"/>
		<set name="baseRandDam" value="10"/>
		<set name="baseAttackType" value="FIST"/>
		<set name="basePHitModify" value="5"/>
		<set name="basePAvoidModify" value="0"/>
		<set name="baseHitTimeFactor" value="0.34"/>
		<set name="baseReuseDelay" value="0"/>
		<set name="baseSafeHeight" value="100"/>
		<set name="aggroRange" value="0"/>
		<set name="shots" value="NONE"/>
		<set name="texture" value=""/>
		<set name="baseDamageRange" value="0;0;80;120"/>
		<skills>
			<skill id="4416" level="7"/>	<!--Spirits-->
			<skill id="4408" level="1"/>	<!--HP Increase (1x)-->
			<skill id="4409" level="1"/>	<!--MP Increase (1x)-->
			<skill id="4410" level="11"/>	<!--Average P. Atk.-->
			<skill id="4411" level="11"/>	<!--Average M. Atk.-->
			<skill id="4412" level="11"/>	<!--Average P. Def.-->
			<skill id="4413" level="11"/>	<!--Average M. Def.-->
			<skill id="4414" level="2"/>	<!--Standard Type-->
			<skill id="4415" level="1"/>	<!--Bare Hands-->
			<skill id="4045" level="1"/>	<!--Resist Full Magic Attack-->
		</skills>
	</npc>
	<npc id="4309" name="Prophet" title="Sinister">
		<set name="type" value="Npc"/>
		<set name="ai_type" value="adept.AdeptGludio"/>
		<set name="collision_height" value="22"/>
		<set name="collision_radius" value="8"/>
		<set name="level" value="70"/>
		<set name="rewardExp" value="0"/>
		<set name="rewardRp" value="0"/>
		<set name="rewardSp" value="0"/>
		<set name="baseHpMax" value="2444.46819"/>
		<set name="baseHpRate" value="1"/>
		<set name="baseHpReg" value="7.5"/>
		<set name="baseMpMax" value="1345.8"/>
		<set name="baseMpReg" value="2.7"/>
		<set name="baseSTR" value="40"/>
		<set name="baseCON" value="43"/>
		<set name="baseDEX" value="30"/>
		<set name="baseINT" value="21"/>
		<set name="baseMEN" value="20"/>
		<set name="baseWIT" value="20"/>
		<set name="basePCritRate" value="40"/>
		<set name="basePAtk" value="688.86373"/>
		<set name="basePDef" value="295.91597"/>
		<set name="basePAtkSpd" value="253"/>
		<set name="baseMAtk" value="470.40463"/>
		<set name="baseMDef" value="216.53847"/>
		<set name="baseWalkSpd" value="50"/>
		<set name="baseRunSpd" value="120"/>
		<set name="baseShldDef" value="0"/>
		<set name="baseShldRate" value="0"/>
		<set name="baseAtkRange" value="40"/>
		<set name="baseRandDam" value="30"/>
		<set name="baseAttackType" value="SWORD"/>
		<set name="basePHitModify" value="5"/>
		<set name="basePAvoidModify" value="0"/>
		<set name="baseHitTimeFactor" value="0.43"/>
		<set name="baseReuseDelay" value="0"/>
		<set name="baseSafeHeight" value="100"/>
		<set name="aggroRange" value="0"/>
		<set name="shots" value="NONE"/>
		<set name="texture" value=""/>
		<set name="baseDamageRange" value="0;0;80;120"/>
		<skills>
			<skill id="4416" level="14"/>	<!--Humans-->
			<skill id="4408" level="1"/>	<!--HP Increase (1x)-->
			<skill id="4409" level="1"/>	<!--MP Increase (1x)-->
			<skill id="4410" level="11"/>	<!--Average P. Atk.-->
			<skill id="4411" level="11"/>	<!--Average M. Atk.-->
			<skill id="4412" level="11"/>	<!--Average P. Def.-->
			<skill id="4413" level="11"/>	<!--Average M. Def.-->
			<skill id="4414" level="2"/>	<!--Standard Type-->
			<skill id="4415" level="3"/>	<!--One-handed Sword-->
			<skill id="4045" level="1"/>	<!--Resist Full Magic Attack-->
		</skills>
	</npc>
	<npc id="4310" name="Prophet" title="Sinister">
		<set name="type" value="Npc"/>
		<set name="ai_type" value="adept.AdeptGiran"/>
		<set name="collision_height" value="22"/>
		<set name="collision_radius" value="8"/>
		<set name="level" value="70"/>
		<set name="rewardExp" value="0"/>
		<set name="rewardRp" value="0"/>
		<set name="rewardSp" value="0"/>
		<set name="baseHpMax" value="2444.46819"/>
		<set name="baseHpRate" value="1"/>
		<set name="baseHpReg" value="7.5"/>
		<set name="baseMpMax" value="1345.8"/>
		<set name="baseMpReg" value="2.7"/>
		<set name="baseSTR" value="40"/>
		<set name="baseCON" value="43"/>
		<set name="baseDEX" value="30"/>
		<set name="baseINT" value="21"/>
		<set name="baseMEN" value="20"/>
		<set name="baseWIT" value="20"/>
		<set name="basePCritRate" value="40"/>
		<set name="basePAtk" value="688.86373"/>
		<set name="basePDef" value="295.91597"/>
		<set name="basePAtkSpd" value="253"/>
		<set name="baseMAtk" value="470.40463"/>
		<set name="baseMDef" value="216.53847"/>
		<set name="baseWalkSpd" value="50"/>
		<set name="baseRunSpd" value="120"/>
		<set name="baseShldDef" value="0"/>
		<set name="baseShldRate" value="0"/>
		<set name="baseAtkRange" value="40"/>
		<set name="baseRandDam" value="30"/>
		<set name="baseAttackType" value="SWORD"/>
		<set name="basePHitModify" value="5"/>
		<set name="basePAvoidModify" value="0"/>
		<set name="baseHitTimeFactor" value="0.43"/>
		<set name="baseReuseDelay" value="0"/>
		<set name="baseSafeHeight" value="100"/>
		<set name="aggroRange" value="0"/>
		<set name="shots" value="NONE"/>
		<set name="texture" value=""/>
		<set name="baseDamageRange" value="0;0;80;120"/>
		<skills>
			<skill id="4416" level="14"/>	<!--Humans-->
			<skill id="4408" level="1"/>	<!--HP Increase (1x)-->
			<skill id="4409" level="1"/>	<!--MP Increase (1x)-->
			<skill id="4410" level="11"/>	<!--Average P. Atk.-->
			<skill id="4411" level="11"/>	<!--Average M. Atk.-->
			<skill id="4412" level="11"/>	<!--Average P. Def.-->
			<skill id="4413" level="11"/>	<!--Average M. Def.-->
			<skill id="4414" level="2"/>	<!--Standard Type-->
			<skill id="4415" level="3"/>	<!--One-handed Sword-->
			<skill id="4045" level="1"/>	<!--Resist Full Magic Attack-->
		</skills>
	</npc>
	<npc id="4311" name="Prophet" title="Sinister">
		<set name="type" value="Npc"/>
		<set name="ai_type" value="adept.AdeptAden"/>
		<set name="collision_height" value="22"/>
		<set name="collision_radius" value="8"/>
		<set name="level" value="70"/>
		<set name="rewardExp" value="0"/>
		<set name="rewardRp" value="0"/>
		<set name="rewardSp" value="0"/>
		<set name="baseHpMax" value="2444.46819"/>
		<set name="baseHpRate" value="1"/>
		<set name="baseHpReg" value="7.5"/>
		<set name="baseMpMax" value="1345.8"/>
		<set name="baseMpReg" value="2.7"/>
		<set name="baseSTR" value="40"/>
		<set name="baseCON" value="43"/>
		<set name="baseDEX" value="30"/>
		<set name="baseINT" value="21"/>
		<set name="baseMEN" value="20"/>
		<set name="baseWIT" value="20"/>
		<set name="basePCritRate" value="40"/>
		<set name="basePAtk" value="688.86373"/>
		<set name="basePDef" value="295.91597"/>
		<set name="basePAtkSpd" value="253"/>
		<set name="baseMAtk" value="470.40463"/>
		<set name="baseMDef" value="216.53847"/>
		<set name="baseWalkSpd" value="50"/>
		<set name="baseRunSpd" value="120"/>
		<set name="baseShldDef" value="0"/>
		<set name="baseShldRate" value="0"/>
		<set name="baseAtkRange" value="40"/>
		<set name="baseRandDam" value="30"/>
		<set name="baseAttackType" value="SWORD"/>
		<set name="basePHitModify" value="5"/>
		<set name="basePAvoidModify" value="0"/>
		<set name="baseHitTimeFactor" value="0.43"/>
		<set name="baseReuseDelay" value="0"/>
		<set name="baseSafeHeight" value="100"/>
		<set name="aggroRange" value="0"/>
		<set name="shots" value="NONE"/>
		<set name="texture" value=""/>
		<set name="baseDamageRange" value="0;0;80;120"/>
		<skills>
			<skill id="4416" level="14"/>	<!--Humans-->
			<skill id="4408" level="1"/>	<!--HP Increase (1x)-->
			<skill id="4409" level="1"/>	<!--MP Increase (1x)-->
			<skill id="4410" level="11"/>	<!--Average P. Atk.-->
			<skill id="4411" level="11"/>	<!--Average M. Atk.-->
			<skill id="4412" level="11"/>	<!--Average P. Def.-->
			<skill id="4413" level="11"/>	<!--Average M. Def.-->
			<skill id="4414" level="2"/>	<!--Standard Type-->
			<skill id="4415" level="3"/>	<!--One-handed Sword-->
			<skill id="4045" level="1"/>	<!--Resist Full Magic Attack-->
		</skills>
	</npc>
	<npc id="4312" name="Prophet" title="Sinister">
		<set name="type" value="Npc"/>
		<set name="ai_type" value="adept.AdeptRune"/>
		<set name="collision_height" value="22"/>
		<set name="collision_radius" value="8"/>
		<set name="level" value="70"/>
		<set name="rewardExp" value="0"/>
		<set name="rewardRp" value="0"/>
		<set name="rewardSp" value="0"/>
		<set name="baseHpMax" value="2444.46819"/>
		<set name="baseHpRate" value="1"/>
		<set name="baseHpReg" value="7.5"/>
		<set name="baseMpMax" value="1345.8"/>
		<set name="baseMpReg" value="2.7"/>
		<set name="baseSTR" value="40"/>
		<set name="baseCON" value="43"/>
		<set name="baseDEX" value="30"/>
		<set name="baseINT" value="21"/>
		<set name="baseMEN" value="20"/>
		<set name="baseWIT" value="20"/>
		<set name="basePCritRate" value="40"/>
		<set name="basePAtk" value="688.86373"/>
		<set name="basePDef" value="295.91597"/>
		<set name="basePAtkSpd" value="253"/>
		<set name="baseMAtk" value="470.40463"/>
		<set name="baseMDef" value="216.53847"/>
		<set name="baseWalkSpd" value="50"/>
		<set name="baseRunSpd" value="120"/>
		<set name="baseShldDef" value="0"/>
		<set name="baseShldRate" value="0"/>
		<set name="baseAtkRange" value="40"/>
		<set name="baseRandDam" value="30"/>
		<set name="baseAttackType" value="SWORD"/>
		<set name="basePHitModify" value="5"/>
		<set name="basePAvoidModify" value="0"/>
		<set name="baseHitTimeFactor" value="0.43"/>
		<set name="baseReuseDelay" value="0"/>
		<set name="baseSafeHeight" value="100"/>
		<set name="aggroRange" value="0"/>
		<set name="shots" value="NONE"/>
		<set name="texture" value=""/>
		<set name="baseDamageRange" value="0;0;80;120"/>
		<skills>
			<skill id="4416" level="14"/>	<!--Humans-->
			<skill id="4408" level="1"/>	<!--HP Increase (1x)-->
			<skill id="4409" level="1"/>	<!--MP Increase (1x)-->
			<skill id="4410" level="11"/>	<!--Average P. Atk.-->
			<skill id="4411" level="11"/>	<!--Average M. Atk.-->
			<skill id="4412" level="11"/>	<!--Average P. Def.-->
			<skill id="4413" level="11"/>	<!--Average M. Def.-->
			<skill id="4414" level="2"/>	<!--Standard Type-->
			<skill id="4415" level="3"/>	<!--One-handed Sword-->
			<skill id="4045" level="1"/>	<!--Resist Full Magic Attack-->
		</skills>
	</npc>
	<npc id="4313" name="Angel Cat" title="Character Collector">
		<set name="type" value="Npc"/>
		<set name="ai_type" value="NpcAI"/>
		<set name="collision_height" value="16"/>
		<set name="collision_radius" value="6"/>
		<set name="level" value="70"/>
		<set name="rewardExp" value="0"/>
		<set name="rewardRp" value="0"/>
		<set name="rewardSp" value="0"/>
		<set name="baseHpMax" value="2444.46819"/>
		<set name="baseHpRate" value="1"/>
		<set name="baseHpReg" value="7.5"/>
		<set name="baseMpMax" value="1345.8"/>
		<set name="baseMpReg" value="2.7"/>
		<set name="baseSTR" value="40"/>
		<set name="baseCON" value="43"/>
		<set name="baseDEX" value="30"/>
		<set name="baseINT" value="21"/>
		<set name="baseMEN" value="20"/>
		<set name="baseWIT" value="20"/>
		<set name="basePCritRate" value="40"/>
		<set name="basePAtk" value="688.86373"/>
		<set name="basePDef" value="295.91597"/>
		<set name="basePAtkSpd" value="253"/>
		<set name="baseMAtk" value="470.40463"/>
		<set name="baseMDef" value="216.53847"/>
		<set name="baseWalkSpd" value="48"/>
		<set name="baseRunSpd" value="140"/>
		<set name="baseShldDef" value="0"/>
		<set name="baseShldRate" value="0"/>
		<set name="baseAtkRange" value="40"/>
		<set name="baseRandDam" value="10"/>
		<set name="baseAttackType" value="FIST"/>
		<set name="basePHitModify" value="5"/>
		<set name="basePAvoidModify" value="0"/>
		<set name="baseHitTimeFactor" value="0.34"/>
		<set name="baseReuseDelay" value="0"/>
		<set name="baseSafeHeight" value="100"/>
		<set name="aggroRange" value="0"/>
		<set name="shots" value="NONE"/>
		<set name="texture" value=""/>
		<set name="baseDamageRange" value="0;0;80;120"/>
		<skills>
			<skill id="4416" level="7"/>	<!--Spirits-->
			<skill id="4408" level="1"/>	<!--HP Increase (1x)-->
			<skill id="4409" level="1"/>	<!--MP Increase (1x)-->
			<skill id="4410" level="11"/>	<!--Average P. Atk.-->
			<skill id="4411" level="11"/>	<!--Average M. Atk.-->
			<skill id="4412" level="11"/>	<!--Average P. Def.-->
			<skill id="4413" level="11"/>	<!--Average M. Def.-->
			<skill id="4414" level="2"/>	<!--Standard Type-->
			<skill id="4415" level="1"/>	<!--Bare Hands-->
			<skill id="4045" level="1"/>	<!--Resist Full Magic Attack-->
		</skills>
	</npc>
	<npc id="4314" name="Teleport Device" title="">
		<set name="type" value="Npc"/>
		<set name="ai_type" value="NpcAI"/>
		<set name="collision_height" value="51.5"/>
		<set name="collision_radius" value="15"/>
		<set name="level" value="70"/>
		<set name="rewardExp" value="0"/>
		<set name="rewardRp" value="0"/>
		<set name="rewardSp" value="0"/>
		<set name="baseHpMax" value="2444.46819"/>
		<set name="baseHpRate" value="1"/>
		<set name="baseHpReg" value="7.5"/>
		<set name="baseMpMax" value="1345.8"/>
		<set name="baseMpReg" value="2.7"/>
		<set name="baseSTR" value="40"/>
		<set name="baseCON" value="43"/>
		<set name="baseDEX" value="30"/>
		<set name="baseINT" value="21"/>
		<set name="baseMEN" value="20"/>
		<set name="baseWIT" value="20"/>
		<set name="basePCritRate" value="40"/>
		<set name="basePAtk" value="688.86373"/>
		<set name="basePDef" value="295.91597"/>
		<set name="basePAtkSpd" value="253"/>
		<set name="baseMAtk" value="470.40463"/>
		<set name="baseMDef" value="216.53847"/>
		<set name="baseWalkSpd" value="1"/>
		<set name="baseRunSpd" value="1"/>
		<set name="baseShldDef" value="0"/>
		<set name="baseShldRate" value="0"/>
		<set name="baseAtkRange" value="40"/>
		<set name="baseRandDam" value="30"/>
		<set name="baseAttackType" value="SWORD"/>
		<set name="basePHitModify" value="5"/>
		<set name="basePAvoidModify" value="0"/>
		<set name="baseHitTimeFactor" value="0.6"/>
		<set name="baseReuseDelay" value="0"/>
		<set name="baseSafeHeight" value="100"/>
		<set name="aggroRange" value="0"/>
		<set name="shots" value="NONE"/>
		<set name="texture" value=""/>
		<set name="baseDamageRange" value="0;0;80;120"/>
		<skills>
			<skill id="4416" level="2"/>	<!--Magic Creatures-->
			<skill id="4408" level="1"/>	<!--HP Increase (1x)-->
			<skill id="4409" level="1"/>	<!--MP Increase (1x)-->
			<skill id="4410" level="11"/>	<!--Average P. Atk.-->
			<skill id="4411" level="11"/>	<!--Average M. Atk.-->
			<skill id="4412" level="11"/>	<!--Average P. Def.-->
			<skill id="4413" level="11"/>	<!--Average M. Def.-->
			<skill id="4414" level="2"/>	<!--Standard Type-->
			<skill id="4415" level="3"/>	<!--One-handed Sword-->
			<skill id="4390" level="1"/>	<!--NPC Abnormal Immunity-->
			<skill id="4045" level="1"/>	<!--Resist Full Magic Attack-->
		</skills>
	</npc>
	<npc id="4315" name="Warehouse Keeper" title="Fantasy Isle Warehouse Keeper">
		<set name="type" value="Warehouse"/>
		<set name="ai_type" value="NpcAI"/>
		<set name="collision_height" value="21.3"/>
		<set name="collision_radius" value="8"/>
		<set name="level" value="70"/>
		<set name="rewardExp" value="0"/>
		<set name="rewardRp" value="0"/>
		<set name="rewardSp" value="0"/>
		<set name="baseHpMax" value="2444.46819"/>
		<set name="baseHpRate" value="1"/>
		<set name="baseHpReg" value="7.5"/>
		<set name="baseMpMax" value="1345.8"/>
		<set name="baseMpReg" value="2.7"/>
		<set name="baseSTR" value="40"/>
		<set name="baseCON" value="43"/>
		<set name="baseDEX" value="30"/>
		<set name="baseINT" value="21"/>
		<set name="baseMEN" value="20"/>
		<set name="baseWIT" value="20"/>
		<set name="basePCritRate" value="40"/>
		<set name="basePAtk" value="688.86373"/>
		<set name="basePDef" value="295.91597"/>
		<set name="basePAtkSpd" value="253"/>
		<set name="baseMAtk" value="470.40463"/>
		<set name="baseMDef" value="216.53847"/>
		<set name="baseWalkSpd" value="50"/>
		<set name="baseRunSpd" value="120"/>
		<set name="baseShldDef" value="0"/>
		<set name="baseShldRate" value="0"/>
		<set name="baseAtkRange" value="40"/>
		<set name="baseRandDam" value="30"/>
		<set name="baseAttackType" value="SWORD"/>
		<set name="basePHitModify" value="5"/>
		<set name="basePAvoidModify" value="0"/>
		<set name="baseHitTimeFactor" value="0.6"/>
		<set name="baseReuseDelay" value="0"/>
		<set name="baseSafeHeight" value="100"/>
		<set name="aggroRange" value="0"/>
		<set name="shots" value="NONE"/>
		<set name="texture" value=""/>
		<set name="baseDamageRange" value="0;0;80;120"/>
		<set name="htm_root" value="Town/FantasyIsle/" />
		<skills>
			<skill id="4416" level="18"/>	<!--Dwarves-->
			<skill id="4408" level="1"/>	<!--HP Increase (1x)-->
			<skill id="4409" level="1"/>	<!--MP Increase (1x)-->
			<skill id="4410" level="11"/>	<!--Average P. Atk.-->
			<skill id="4411" level="11"/>	<!--Average M. Atk.-->
			<skill id="4412" level="11"/>	<!--Average P. Def.-->
			<skill id="4413" level="11"/>	<!--Average M. Def.-->
			<skill id="4414" level="2"/>	<!--Standard Type-->
			<skill id="4415" level="3"/>	<!--One-handed Sword-->
			<skill id="4045" level="1"/>	<!--Resist Full Magic Attack-->
		</skills>
	</npc>
	<npc id="4316" name="Kind Sno" title="Photo NPC">
		<set name="type" value="Npc"/>
		<set name="ai_type" value="NpcAI"/>
		<set name="collision_height" value="16.3"/>
		<set name="collision_radius" value="9"/>
		<set name="level" value="55"/>
		<set name="rewardExp" value="0"/>
		<set name="rewardRp" value="0"/>
		<set name="rewardSp" value="0"/>
		<set name="baseHpMax" value="1673.05473"/>
		<set name="baseHpRate" value="1"/>
		<set name="baseHpReg" value="6.5"/>
		<set name="baseMpMax" value="889.8"/>
		<set name="baseMpReg" value="2.4"/>
		<set name="baseSTR" value="40"/>
		<set name="baseCON" value="43"/>
		<set name="baseDEX" value="30"/>
		<set name="baseINT" value="21"/>
		<set name="baseMEN" value="25"/>
		<set name="baseWIT" value="20"/>
		<set name="basePCritRate" value="40"/>
		<set name="basePAtk" value="388.11142"/>
		<set name="basePDef" value="223.6362"/>
		<set name="basePAtkSpd" value="253"/>
		<set name="baseMAtk" value="265.02979"/>
		<set name="baseMDef" value="163.64727"/>
		<set name="baseWalkSpd" value="4"/>
		<set name="baseRunSpd" value="180"/>
		<set name="baseShldDef" value="0"/>
		<set name="baseShldRate" value="0"/>
		<set name="baseAtkRange" value="40"/>
		<set name="baseRandDam" value="10"/>
		<set name="baseAttackType" value="FIST"/>
		<set name="basePHitModify" value="4.75"/>
		<set name="basePAvoidModify" value="0"/>
		<set name="baseHitTimeFactor" value="0.6"/>
		<set name="baseReuseDelay" value="0"/>
		<set name="baseSafeHeight" value="100"/>
		<set name="aggroRange" value="0"/>
		<set name="shots" value="NONE"/>
		<set name="texture" value=""/>
		<set name="baseDamageRange" value="0;0;80;120"/>
		<set name="htm_root" value="Town/FantasyIsle/" />
		<ai_params>
			<set name="spiritshot_count" value="2"/>
			<set name="soulshot_count" value="2"/>
		</ai_params>
		<skills>
			<skill id="4416" level="7"/>	<!--Spirits-->
			<skill id="4408" level="1"/>	<!--HP Increase (1x)-->
			<skill id="4409" level="1"/>	<!--MP Increase (1x)-->
			<skill id="4410" level="11"/>	<!--Average P. Atk.-->
			<skill id="4411" level="11"/>	<!--Average M. Atk.-->
			<skill id="4412" level="11"/>	<!--Average P. Def.-->
			<skill id="4413" level="11"/>	<!--Average M. Def.-->
			<skill id="4414" level="2"/>	<!--Standard Type-->
			<skill id="4415" level="1"/>	<!--Bare Hands-->
		</skills>
	</npc>
	<npc id="4317" name="Kind Sno" title="Photo NPC">
		<set name="type" value="Npc"/>
		<set name="ai_type" value="NpcAI"/>
		<set name="collision_height" value="16.3"/>
		<set name="collision_radius" value="9"/>
		<set name="level" value="55"/>
		<set name="rewardExp" value="0"/>
		<set name="rewardRp" value="0"/>
		<set name="rewardSp" value="0"/>
		<set name="baseHpMax" value="1673.05473"/>
		<set name="baseHpRate" value="1"/>
		<set name="baseHpReg" value="6.5"/>
		<set name="baseMpMax" value="889.8"/>
		<set name="baseMpReg" value="2.4"/>
		<set name="baseSTR" value="40"/>
		<set name="baseCON" value="43"/>
		<set name="baseDEX" value="30"/>
		<set name="baseINT" value="21"/>
		<set name="baseMEN" value="25"/>
		<set name="baseWIT" value="20"/>
		<set name="basePCritRate" value="40"/>
		<set name="basePAtk" value="388.11142"/>
		<set name="basePDef" value="223.6362"/>
		<set name="basePAtkSpd" value="253"/>
		<set name="baseMAtk" value="265.02979"/>
		<set name="baseMDef" value="163.64727"/>
		<set name="baseWalkSpd" value="4"/>
		<set name="baseRunSpd" value="180"/>
		<set name="baseShldDef" value="0"/>
		<set name="baseShldRate" value="0"/>
		<set name="baseAtkRange" value="40"/>
		<set name="baseRandDam" value="10"/>
		<set name="baseAttackType" value="FIST"/>
		<set name="basePHitModify" value="4.75"/>
		<set name="basePAvoidModify" value="0"/>
		<set name="baseHitTimeFactor" value="0.6"/>
		<set name="baseReuseDelay" value="0"/>
		<set name="baseSafeHeight" value="100"/>
		<set name="aggroRange" value="0"/>
		<set name="shots" value="NONE"/>
		<set name="texture" value=""/>
		<set name="baseDamageRange" value="0;0;80;120"/>
		<set name="htm_root" value="Town/FantasyIsle/" />
		<ai_params>
			<set name="spiritshot_count" value="2"/>
			<set name="soulshot_count" value="2"/>
		</ai_params>
		<skills>
			<skill id="4416" level="7"/>	<!--Spirits-->
			<skill id="4408" level="1"/>	<!--HP Increase (1x)-->
			<skill id="4409" level="1"/>	<!--MP Increase (1x)-->
			<skill id="4410" level="11"/>	<!--Average P. Atk.-->
			<skill id="4411" level="11"/>	<!--Average M. Atk.-->
			<skill id="4412" level="11"/>	<!--Average P. Def.-->
			<skill id="4413" level="11"/>	<!--Average M. Def.-->
			<skill id="4414" level="2"/>	<!--Standard Type-->
			<skill id="4415" level="1"/>	<!--Bare Hands-->
		</skills>
	</npc>
	<npc id="4318" name="Kind Sno" title="Photo NPC">
		<set name="type" value="Npc"/>
		<set name="ai_type" value="NpcAI"/>
		<set name="collision_height" value="16.3"/>
		<set name="collision_radius" value="9"/>
		<set name="level" value="55"/>
		<set name="rewardExp" value="0"/>
		<set name="rewardRp" value="0"/>
		<set name="rewardSp" value="0"/>
		<set name="baseHpMax" value="1673.05473"/>
		<set name="baseHpRate" value="1"/>
		<set name="baseHpReg" value="6.5"/>
		<set name="baseMpMax" value="889.8"/>
		<set name="baseMpReg" value="2.4"/>
		<set name="baseSTR" value="40"/>
		<set name="baseCON" value="43"/>
		<set name="baseDEX" value="30"/>
		<set name="baseINT" value="21"/>
		<set name="baseMEN" value="25"/>
		<set name="baseWIT" value="20"/>
		<set name="basePCritRate" value="40"/>
		<set name="basePAtk" value="388.11142"/>
		<set name="basePDef" value="223.6362"/>
		<set name="basePAtkSpd" value="253"/>
		<set name="baseMAtk" value="265.02979"/>
		<set name="baseMDef" value="163.64727"/>
		<set name="baseWalkSpd" value="4"/>
		<set name="baseRunSpd" value="180"/>
		<set name="baseShldDef" value="0"/>
		<set name="baseShldRate" value="0"/>
		<set name="baseAtkRange" value="40"/>
		<set name="baseRandDam" value="10"/>
		<set name="baseAttackType" value="FIST"/>
		<set name="basePHitModify" value="4.75"/>
		<set name="basePAvoidModify" value="0"/>
		<set name="baseHitTimeFactor" value="0.6"/>
		<set name="baseReuseDelay" value="0"/>
		<set name="baseSafeHeight" value="100"/>
		<set name="aggroRange" value="0"/>
		<set name="shots" value="NONE"/>
		<set name="texture" value=""/>
		<set name="baseDamageRange" value="0;0;80;120"/>
		<set name="htm_root" value="Town/FantasyIsle/" />
		<ai_params>
			<set name="spiritshot_count" value="2"/>
			<set name="soulshot_count" value="2"/>
		</ai_params>
		<skills>
			<skill id="4416" level="7"/>	<!--Spirits-->
			<skill id="4408" level="1"/>	<!--HP Increase (1x)-->
			<skill id="4409" level="1"/>	<!--MP Increase (1x)-->
			<skill id="4410" level="11"/>	<!--Average P. Atk.-->
			<skill id="4411" level="11"/>	<!--Average M. Atk.-->
			<skill id="4412" level="11"/>	<!--Average P. Def.-->
			<skill id="4413" level="11"/>	<!--Average M. Def.-->
			<skill id="4414" level="2"/>	<!--Standard Type-->
			<skill id="4415" level="1"/>	<!--Bare Hands-->
		</skills>
	</npc>
	<npc id="4319" name="Kind Sno" title="Photo NPC">
		<set name="type" value="Npc"/>
		<set name="ai_type" value="NpcAI"/>
		<set name="collision_height" value="16.3"/>
		<set name="collision_radius" value="9"/>
		<set name="level" value="55"/>
		<set name="rewardExp" value="0"/>
		<set name="rewardRp" value="0"/>
		<set name="rewardSp" value="0"/>
		<set name="baseHpMax" value="1673.05473"/>
		<set name="baseHpRate" value="1"/>
		<set name="baseHpReg" value="6.5"/>
		<set name="baseMpMax" value="889.8"/>
		<set name="baseMpReg" value="2.4"/>
		<set name="baseSTR" value="40"/>
		<set name="baseCON" value="43"/>
		<set name="baseDEX" value="30"/>
		<set name="baseINT" value="21"/>
		<set name="baseMEN" value="25"/>
		<set name="baseWIT" value="20"/>
		<set name="basePCritRate" value="40"/>
		<set name="basePAtk" value="388.11142"/>
		<set name="basePDef" value="223.6362"/>
		<set name="basePAtkSpd" value="253"/>
		<set name="baseMAtk" value="265.02979"/>
		<set name="baseMDef" value="163.64727"/>
		<set name="baseWalkSpd" value="4"/>
		<set name="baseRunSpd" value="180"/>
		<set name="baseShldDef" value="0"/>
		<set name="baseShldRate" value="0"/>
		<set name="baseAtkRange" value="40"/>
		<set name="baseRandDam" value="10"/>
		<set name="baseAttackType" value="FIST"/>
		<set name="basePHitModify" value="4.75"/>
		<set name="basePAvoidModify" value="0"/>
		<set name="baseHitTimeFactor" value="0.6"/>
		<set name="baseReuseDelay" value="0"/>
		<set name="baseSafeHeight" value="100"/>
		<set name="aggroRange" value="0"/>
		<set name="shots" value="NONE"/>
		<set name="texture" value=""/>
		<set name="baseDamageRange" value="0;0;80;120"/>
		<set name="htm_root" value="Town/FantasyIsle/" />
		<ai_params>
			<set name="spiritshot_count" value="2"/>
			<set name="soulshot_count" value="2"/>
		</ai_params>
		<skills>
			<skill id="4416" level="7"/>	<!--Spirits-->
			<skill id="4408" level="1"/>	<!--HP Increase (1x)-->
			<skill id="4409" level="1"/>	<!--MP Increase (1x)-->
			<skill id="4410" level="11"/>	<!--Average P. Atk.-->
			<skill id="4411" level="11"/>	<!--Average M. Atk.-->
			<skill id="4412" level="11"/>	<!--Average P. Def.-->
			<skill id="4413" level="11"/>	<!--Average M. Def.-->
			<skill id="4414" level="2"/>	<!--Standard Type-->
			<skill id="4415" level="1"/>	<!--Bare Hands-->
		</skills>
	</npc>
	<npc id="4320" name="Kind Sno" title="Photo NPC">
		<set name="type" value="Npc"/>
		<set name="ai_type" value="NpcAI"/>
		<set name="collision_height" value="16.3"/>
		<set name="collision_radius" value="9"/>
		<set name="level" value="55"/>
		<set name="rewardExp" value="0"/>
		<set name="rewardRp" value="0"/>
		<set name="rewardSp" value="0"/>
		<set name="baseHpMax" value="1673.05473"/>
		<set name="baseHpRate" value="1"/>
		<set name="baseHpReg" value="6.5"/>
		<set name="baseMpMax" value="889.8"/>
		<set name="baseMpReg" value="2.4"/>
		<set name="baseSTR" value="40"/>
		<set name="baseCON" value="43"/>
		<set name="baseDEX" value="30"/>
		<set name="baseINT" value="21"/>
		<set name="baseMEN" value="25"/>
		<set name="baseWIT" value="20"/>
		<set name="basePCritRate" value="40"/>
		<set name="basePAtk" value="388.11142"/>
		<set name="basePDef" value="223.6362"/>
		<set name="basePAtkSpd" value="253"/>
		<set name="baseMAtk" value="265.02979"/>
		<set name="baseMDef" value="163.64727"/>
		<set name="baseWalkSpd" value="4"/>
		<set name="baseRunSpd" value="180"/>
		<set name="baseShldDef" value="0"/>
		<set name="baseShldRate" value="0"/>
		<set name="baseAtkRange" value="40"/>
		<set name="baseRandDam" value="10"/>
		<set name="baseAttackType" value="FIST"/>
		<set name="basePHitModify" value="4.75"/>
		<set name="basePAvoidModify" value="0"/>
		<set name="baseHitTimeFactor" value="0.6"/>
		<set name="baseReuseDelay" value="0"/>
		<set name="baseSafeHeight" value="100"/>
		<set name="aggroRange" value="0"/>
		<set name="shots" value="NONE"/>
		<set name="texture" value=""/>
		<set name="baseDamageRange" value="0;0;80;120"/>
		<set name="htm_root" value="Town/FantasyIsle/" />
		<ai_params>
			<set name="spiritshot_count" value="2"/>
			<set name="soulshot_count" value="2"/>
		</ai_params>
		<skills>
			<skill id="4416" level="7"/>	<!--Spirits-->
			<skill id="4408" level="1"/>	<!--HP Increase (1x)-->
			<skill id="4409" level="1"/>	<!--MP Increase (1x)-->
			<skill id="4410" level="11"/>	<!--Average P. Atk.-->
			<skill id="4411" level="11"/>	<!--Average M. Atk.-->
			<skill id="4412" level="11"/>	<!--Average P. Def.-->
			<skill id="4413" level="11"/>	<!--Average M. Def.-->
			<skill id="4414" level="2"/>	<!--Standard Type-->
			<skill id="4415" level="1"/>	<!--Bare Hands-->
		</skills>
	</npc>
	<npc id="4321" name="Kind Sno" title="Photo NPC">
		<set name="type" value="Npc"/>
		<set name="ai_type" value="NpcAI"/>
		<set name="collision_height" value="16.3"/>
		<set name="collision_radius" value="9"/>
		<set name="level" value="55"/>
		<set name="rewardExp" value="0"/>
		<set name="rewardRp" value="0"/>
		<set name="rewardSp" value="0"/>
		<set name="baseHpMax" value="1673.05473"/>
		<set name="baseHpRate" value="1"/>
		<set name="baseHpReg" value="6.5"/>
		<set name="baseMpMax" value="889.8"/>
		<set name="baseMpReg" value="2.4"/>
		<set name="baseSTR" value="40"/>
		<set name="baseCON" value="43"/>
		<set name="baseDEX" value="30"/>
		<set name="baseINT" value="21"/>
		<set name="baseMEN" value="25"/>
		<set name="baseWIT" value="20"/>
		<set name="basePCritRate" value="40"/>
		<set name="basePAtk" value="388.11142"/>
		<set name="basePDef" value="223.6362"/>
		<set name="basePAtkSpd" value="253"/>
		<set name="baseMAtk" value="265.02979"/>
		<set name="baseMDef" value="163.64727"/>
		<set name="baseWalkSpd" value="4"/>
		<set name="baseRunSpd" value="180"/>
		<set name="baseShldDef" value="0"/>
		<set name="baseShldRate" value="0"/>
		<set name="baseAtkRange" value="40"/>
		<set name="baseRandDam" value="10"/>
		<set name="baseAttackType" value="FIST"/>
		<set name="basePHitModify" value="4.75"/>
		<set name="basePAvoidModify" value="0"/>
		<set name="baseHitTimeFactor" value="0.6"/>
		<set name="baseReuseDelay" value="0"/>
		<set name="baseSafeHeight" value="100"/>
		<set name="aggroRange" value="0"/>
		<set name="shots" value="NONE"/>
		<set name="texture" value=""/>
		<set name="baseDamageRange" value="0;0;80;120"/>
		<set name="htm_root" value="Town/FantasyIsle/" />
		<ai_params>
			<set name="spiritshot_count" value="2"/>
			<set name="soulshot_count" value="2"/>
		</ai_params>
		<skills>
			<skill id="4416" level="7"/>	<!--Spirits-->
			<skill id="4408" level="1"/>	<!--HP Increase (1x)-->
			<skill id="4409" level="1"/>	<!--MP Increase (1x)-->
			<skill id="4410" level="11"/>	<!--Average P. Atk.-->
			<skill id="4411" level="11"/>	<!--Average M. Atk.-->
			<skill id="4412" level="11"/>	<!--Average P. Def.-->
			<skill id="4413" level="11"/>	<!--Average M. Def.-->
			<skill id="4414" level="2"/>	<!--Standard Type-->
			<skill id="4415" level="1"/>	<!--Bare Hands-->
		</skills>
	</npc>
	<npc id="4322" name="Kind Sno" title="Photo NPC">
		<set name="type" value="Npc"/>
		<set name="ai_type" value="NpcAI"/>
		<set name="collision_height" value="16.3"/>
		<set name="collision_radius" value="9"/>
		<set name="level" value="55"/>
		<set name="rewardExp" value="0"/>
		<set name="rewardRp" value="0"/>
		<set name="rewardSp" value="0"/>
		<set name="baseHpMax" value="1673.05473"/>
		<set name="baseHpRate" value="1"/>
		<set name="baseHpReg" value="6.5"/>
		<set name="baseMpMax" value="889.8"/>
		<set name="baseMpReg" value="2.4"/>
		<set name="baseSTR" value="40"/>
		<set name="baseCON" value="43"/>
		<set name="baseDEX" value="30"/>
		<set name="baseINT" value="21"/>
		<set name="baseMEN" value="25"/>
		<set name="baseWIT" value="20"/>
		<set name="basePCritRate" value="40"/>
		<set name="basePAtk" value="388.11142"/>
		<set name="basePDef" value="223.6362"/>
		<set name="basePAtkSpd" value="253"/>
		<set name="baseMAtk" value="265.02979"/>
		<set name="baseMDef" value="163.64727"/>
		<set name="baseWalkSpd" value="4"/>
		<set name="baseRunSpd" value="180"/>
		<set name="baseShldDef" value="0"/>
		<set name="baseShldRate" value="0"/>
		<set name="baseAtkRange" value="40"/>
		<set name="baseRandDam" value="10"/>
		<set name="baseAttackType" value="FIST"/>
		<set name="basePHitModify" value="4.75"/>
		<set name="basePAvoidModify" value="0"/>
		<set name="baseHitTimeFactor" value="0.6"/>
		<set name="baseReuseDelay" value="0"/>
		<set name="baseSafeHeight" value="100"/>
		<set name="aggroRange" value="0"/>
		<set name="shots" value="NONE"/>
		<set name="texture" value=""/>
		<set name="baseDamageRange" value="0;0;80;120"/>
		<set name="htm_root" value="Town/FantasyIsle/" />
		<ai_params>
			<set name="spiritshot_count" value="2"/>
			<set name="soulshot_count" value="2"/>
		</ai_params>
		<skills>
			<skill id="4416" level="7"/>	<!--Spirits-->
			<skill id="4408" level="1"/>	<!--HP Increase (1x)-->
			<skill id="4409" level="1"/>	<!--MP Increase (1x)-->
			<skill id="4410" level="11"/>	<!--Average P. Atk.-->
			<skill id="4411" level="11"/>	<!--Average M. Atk.-->
			<skill id="4412" level="11"/>	<!--Average P. Def.-->
			<skill id="4413" level="11"/>	<!--Average M. Def.-->
			<skill id="4414" level="2"/>	<!--Standard Type-->
			<skill id="4415" level="1"/>	<!--Bare Hands-->
		</skills>
	</npc>
	<npc id="4323" name="Kind Sno" title="Photo NPC">
		<set name="type" value="Npc"/>
		<set name="ai_type" value="NpcAI"/>
		<set name="collision_height" value="16.3"/>
		<set name="collision_radius" value="9"/>
		<set name="level" value="55"/>
		<set name="rewardExp" value="0"/>
		<set name="rewardRp" value="0"/>
		<set name="rewardSp" value="0"/>
		<set name="baseHpMax" value="1673.05473"/>
		<set name="baseHpRate" value="1"/>
		<set name="baseHpReg" value="6.5"/>
		<set name="baseMpMax" value="889.8"/>
		<set name="baseMpReg" value="2.4"/>
		<set name="baseSTR" value="40"/>
		<set name="baseCON" value="43"/>
		<set name="baseDEX" value="30"/>
		<set name="baseINT" value="21"/>
		<set name="baseMEN" value="25"/>
		<set name="baseWIT" value="20"/>
		<set name="basePCritRate" value="40"/>
		<set name="basePAtk" value="388.11142"/>
		<set name="basePDef" value="223.6362"/>
		<set name="basePAtkSpd" value="253"/>
		<set name="baseMAtk" value="265.02979"/>
		<set name="baseMDef" value="163.64727"/>
		<set name="baseWalkSpd" value="4"/>
		<set name="baseRunSpd" value="180"/>
		<set name="baseShldDef" value="0"/>
		<set name="baseShldRate" value="0"/>
		<set name="baseAtkRange" value="40"/>
		<set name="baseRandDam" value="10"/>
		<set name="baseAttackType" value="FIST"/>
		<set name="basePHitModify" value="4.75"/>
		<set name="basePAvoidModify" value="0"/>
		<set name="baseHitTimeFactor" value="0.6"/>
		<set name="baseReuseDelay" value="0"/>
		<set name="baseSafeHeight" value="100"/>
		<set name="aggroRange" value="0"/>
		<set name="shots" value="NONE"/>
		<set name="texture" value=""/>
		<set name="baseDamageRange" value="0;0;80;120"/>
		<set name="htm_root" value="Town/FantasyIsle/" />
		<ai_params>
			<set name="spiritshot_count" value="2"/>
			<set name="soulshot_count" value="2"/>
		</ai_params>
		<skills>
			<skill id="4416" level="7"/>	<!--Spirits-->
			<skill id="4408" level="1"/>	<!--HP Increase (1x)-->
			<skill id="4409" level="1"/>	<!--MP Increase (1x)-->
			<skill id="4410" level="11"/>	<!--Average P. Atk.-->
			<skill id="4411" level="11"/>	<!--Average M. Atk.-->
			<skill id="4412" level="11"/>	<!--Average P. Def.-->
			<skill id="4413" level="11"/>	<!--Average M. Def.-->
			<skill id="4414" level="2"/>	<!--Standard Type-->
			<skill id="4415" level="1"/>	<!--Bare Hands-->
		</skills>
	</npc>
	<npc id="4324" name="Worshipper" title="Sinister">
		<set name="type" value="Npc"/>
		<set name="ai_type" value="NpcAI"/>
		<set name="collision_height" value="22"/>
		<set name="collision_radius" value="8"/>
		<set name="level" value="70"/>
		<set name="rewardExp" value="0"/>
		<set name="rewardRp" value="0"/>
		<set name="rewardSp" value="0"/>
		<set name="baseHpMax" value="2444.46819"/>
		<set name="baseHpRate" value="1"/>
		<set name="baseHpReg" value="7.5"/>
		<set name="baseMpMax" value="1345.8"/>
		<set name="baseMpReg" value="2.7"/>
		<set name="baseSTR" value="40"/>
		<set name="baseCON" value="43"/>
		<set name="baseDEX" value="30"/>
		<set name="baseINT" value="21"/>
		<set name="baseMEN" value="20"/>
		<set name="baseWIT" value="20"/>
		<set name="basePCritRate" value="40"/>
		<set name="basePAtk" value="688.86373"/>
		<set name="basePDef" value="295.91597"/>
		<set name="basePAtkSpd" value="253"/>
		<set name="baseMAtk" value="470.40463"/>
		<set name="baseMDef" value="216.53847"/>
		<set name="baseWalkSpd" value="50"/>
		<set name="baseRunSpd" value="120"/>
		<set name="baseShldDef" value="0"/>
		<set name="baseShldRate" value="0"/>
		<set name="baseAtkRange" value="40"/>
		<set name="baseRandDam" value="30"/>
		<set name="baseAttackType" value="SWORD"/>
		<set name="basePHitModify" value="5"/>
		<set name="basePAvoidModify" value="0"/>
		<set name="baseHitTimeFactor" value="0.6"/>
		<set name="baseReuseDelay" value="0"/>
		<set name="baseSafeHeight" value="100"/>
		<set name="aggroRange" value="0"/>
		<set name="shots" value="NONE"/>
		<set name="texture" value=""/>
		<set name="baseDamageRange" value="0;0;80;120"/>
		<skills>
			<skill id="4416" level="14"/>	<!--Humans-->
			<skill id="4408" level="1"/>	<!--HP Increase (1x)-->
			<skill id="4409" level="1"/>	<!--MP Increase (1x)-->
			<skill id="4410" level="11"/>	<!--Average P. Atk.-->
			<skill id="4411" level="11"/>	<!--Average M. Atk.-->
			<skill id="4412" level="11"/>	<!--Average P. Def.-->
			<skill id="4413" level="11"/>	<!--Average M. Def.-->
			<skill id="4414" level="2"/>	<!--Standard Type-->
			<skill id="4415" level="3"/>	<!--One-handed Sword-->
			<skill id="4045" level="1"/>	<!--Resist Full Magic Attack-->
		</skills>
	</npc>
	<npc id="4325" name="Altar Guard" title="">
		<set name="type" value="Guard"/>
		<set name="ai_type" value="Guard"/>
		<set name="collision_height" value="24"/>
		<set name="collision_radius" value="8"/>
		<set name="level" value="70"/>
		<set name="rewardExp" value="0"/>
		<set name="rewardRp" value="0"/>
		<set name="rewardSp" value="0"/>
		<set name="baseHpMax" value="3290.11306877694"/>
		<set name="baseHpRate" value="1"/>
		<set name="baseHpReg" value="8.5"/>
		<set name="baseMpMax" value="1674.8"/>
		<set name="baseMpReg" value="3"/>
		<set name="baseSTR" value="40"/>
		<set name="baseCON" value="43"/>
		<set name="baseDEX" value="30"/>
		<set name="baseINT" value="21"/>
		<set name="baseMEN" value="20"/>
		<set name="baseWIT" value="20"/>
		<set name="basePCritRate" value="40"/>
		<set name="basePAtk" value="970.537548504614"/>
		<set name="basePDef" value="341.375"/>
		<set name="basePAtkSpd" value="253"/>
		<set name="baseMAtk" value="662.751329129412"/>
		<set name="baseMDef" value="249.80341"/>
		<set name="baseWalkSpd" value="50"/>
		<set name="baseRunSpd" value="160"/>
		<set name="baseShldDef" value="147.957985"/>
		<set name="baseShldRate" value="20"/>
		<set name="baseAtkRange" value="40"/>
		<set name="baseRandDam" value="30"/>
		<set name="baseAttackType" value="SWORD"/>
		<set name="basePHitModify" value="5"/>
		<set name="basePAvoidModify" value="0"/>
		<set name="baseHitTimeFactor" value="0.6"/>
		<set name="baseReuseDelay" value="0"/>
		<set name="baseSafeHeight" value="100"/>
		<set name="aggroRange" value="1000"/>
		<set name="shots" value="NONE"/>
		<set name="texture" value=""/>
		<set name="baseDamageRange" value="0;0;80;120"/>
		<equip>
			<rhand item_id="2"/>	<!--Long Sword-->
			<lhand item_id="20"/>	<!--Buckler-->
		</equip>
		<skills>
			<skill id="4416" level="14"/>	<!--Humans-->
			<skill id="4408" level="1"/>	<!--HP Increase (1x)-->
			<skill id="4409" level="1"/>	<!--MP Increase (1x)-->
			<skill id="4410" level="16"/>	<!--Very Strong P. Atk.-->
			<skill id="4411" level="16"/>	<!--Very Strong M. Atk.-->
			<skill id="4412" level="16"/>	<!--Very Strong P. Def.-->
			<skill id="4413" level="16"/>	<!--Very Strong M. Def.-->
			<skill id="4414" level="2"/>	<!--Standard Type-->
			<skill id="4415" level="3"/>	<!--One-handed Sword-->
			<skill id="4045" level="1"/>	<!--Resist Full Magic Attack-->
		</skills>
	</npc>
	<npc id="4326" name="Nevit's Herald" title="Invoker">
		<set name="type" value="NevitHerald"/>
		<set name="ai_type" value="NpcAI"/>
		<set name="collision_height" value="22.5"/>
		<set name="collision_radius" value="8"/>
		<set name="level" value="80"/>
		<set name="rewardExp" value="0"/>
		<set name="rewardRp" value="0"/>
		<set name="rewardSp" value="0"/>
		<set name="baseHpMax" value="3290.11306877694"/>
		<set name="baseHpRate" value="1"/>
		<set name="baseHpReg" value="8.5"/>
		<set name="baseMpMax" value="1674.8"/>
		<set name="baseMpReg" value="3"/>
		<set name="baseSTR" value="40"/>
		<set name="baseCON" value="43"/>
		<set name="baseDEX" value="30"/>
		<set name="baseINT" value="21"/>
		<set name="baseMEN" value="20"/>
		<set name="baseWIT" value="20"/>
		<set name="basePCritRate" value="40"/>
		<set name="basePAtk" value="970.537548504614"/>
		<set name="basePDef" value="341.375"/>
		<set name="basePAtkSpd" value="253"/>
		<set name="baseMAtk" value="662.751329129412"/>
		<set name="baseMDef" value="249.80341"/>
		<set name="baseWalkSpd" value="50"/>
		<set name="baseRunSpd" value="120"/>
		<set name="baseShldDef" value="0"/>
		<set name="baseShldRate" value="0"/>
		<set name="baseAtkRange" value="40"/>
		<set name="baseRandDam" value="10"/>
		<set name="baseAttackType" value="FIST"/>
		<set name="basePHitModify" value="5"/>
		<set name="basePAvoidModify" value="0"/>
		<set name="baseHitTimeFactor" value="0.6"/>
		<set name="baseReuseDelay" value="0"/>
		<set name="baseSafeHeight" value="100"/>
		<set name="aggroRange" value="0"/>
		<set name="shots" value="NONE"/>
		<set name="texture" value=""/>
		<set name="baseDamageRange" value="0;0;80;120"/>
		<skills>
			<skill id="4416" level="14"/>	<!--Humans-->
			<skill id="4408" level="1"/>	<!--HP Increase (1x)-->
			<skill id="4409" level="1"/>	<!--MP Increase (1x)-->
			<skill id="4410" level="11"/>	<!--Average P. Atk.-->
			<skill id="4411" level="11"/>	<!--Average M. Atk.-->
			<skill id="4412" level="11"/>	<!--Average P. Def.-->
			<skill id="4413" level="11"/>	<!--Average M. Def.-->
			<skill id="4414" level="2"/>	<!--Standard Type-->
			<skill id="4415" level="1"/>	<!--Bare Hands-->
			<skill id="4045" level="1"/>	<!--Resist Full Magic Attack-->
		</skills>
	</npc>
	<npc id="4327" name="Worshipper" title="Sinister">
		<set name="type" value="Npc"/>
		<set name="ai_type" value="NpcAI"/>
		<set name="collision_height" value="22"/>
		<set name="collision_radius" value="8"/>
		<set name="level" value="70"/>
		<set name="rewardExp" value="0"/>
		<set name="rewardRp" value="0"/>
		<set name="rewardSp" value="0"/>
		<set name="baseHpMax" value="2444.46819"/>
		<set name="baseHpRate" value="1"/>
		<set name="baseHpReg" value="7.5"/>
		<set name="baseMpMax" value="1345.8"/>
		<set name="baseMpReg" value="2.7"/>
		<set name="baseSTR" value="40"/>
		<set name="baseCON" value="43"/>
		<set name="baseDEX" value="30"/>
		<set name="baseINT" value="21"/>
		<set name="baseMEN" value="20"/>
		<set name="baseWIT" value="20"/>
		<set name="basePCritRate" value="40"/>
		<set name="basePAtk" value="688.86373"/>
		<set name="basePDef" value="295.91597"/>
		<set name="basePAtkSpd" value="253"/>
		<set name="baseMAtk" value="470.40463"/>
		<set name="baseMDef" value="216.53847"/>
		<set name="baseWalkSpd" value="50"/>
		<set name="baseRunSpd" value="120"/>
		<set name="baseShldDef" value="0"/>
		<set name="baseShldRate" value="0"/>
		<set name="baseAtkRange" value="40"/>
		<set name="baseRandDam" value="30"/>
		<set name="baseAttackType" value="SWORD"/>
		<set name="basePHitModify" value="5"/>
		<set name="basePAvoidModify" value="0"/>
		<set name="baseHitTimeFactor" value="0.6"/>
		<set name="baseReuseDelay" value="0"/>
		<set name="baseSafeHeight" value="100"/>
		<set name="aggroRange" value="0"/>
		<set name="shots" value="NONE"/>
		<set name="texture" value=""/>
		<set name="baseDamageRange" value="0;0;80;120"/>
		<skills>
			<skill id="4416" level="14"/>	<!--Humans-->
			<skill id="4408" level="1"/>	<!--HP Increase (1x)-->
			<skill id="4409" level="1"/>	<!--MP Increase (1x)-->
			<skill id="4410" level="11"/>	<!--Average P. Atk.-->
			<skill id="4411" level="11"/>	<!--Average M. Atk.-->
			<skill id="4412" level="11"/>	<!--Average P. Def.-->
			<skill id="4413" level="11"/>	<!--Average M. Def.-->
			<skill id="4414" level="2"/>	<!--Standard Type-->
			<skill id="4415" level="3"/>	<!--One-handed Sword-->
			<skill id="4045" level="1"/>	<!--Resist Full Magic Attack-->
		</skills>
	</npc>
	<npc id="4328" name="Altar Guard" title="">
		<set name="type" value="Npc"/>
		<set name="ai_type" value="NpcAI"/>
		<set name="collision_height" value="24"/>
		<set name="collision_radius" value="8"/>
		<set name="level" value="70"/>
		<set name="rewardExp" value="0"/>
		<set name="rewardRp" value="0"/>
		<set name="rewardSp" value="0"/>
		<set name="baseHpMax" value="3290.11306877694"/>
		<set name="baseHpRate" value="1"/>
		<set name="baseHpReg" value="8.5"/>
		<set name="baseMpMax" value="1674.8"/>
		<set name="baseMpReg" value="3"/>
		<set name="baseSTR" value="40"/>
		<set name="baseCON" value="43"/>
		<set name="baseDEX" value="30"/>
		<set name="baseINT" value="21"/>
		<set name="baseMEN" value="20"/>
		<set name="baseWIT" value="20"/>
		<set name="basePCritRate" value="40"/>
		<set name="basePAtk" value="970.537548504614"/>
		<set name="basePDef" value="341.375"/>
		<set name="basePAtkSpd" value="253"/>
		<set name="baseMAtk" value="662.751329129412"/>
		<set name="baseMDef" value="249.80341"/>
		<set name="baseWalkSpd" value="50"/>
		<set name="baseRunSpd" value="160"/>
		<set name="baseShldDef" value="147.957985"/>
		<set name="baseShldRate" value="20"/>
		<set name="baseAtkRange" value="40"/>
		<set name="baseRandDam" value="30"/>
		<set name="baseAttackType" value="SWORD"/>
		<set name="basePHitModify" value="5"/>
		<set name="basePAvoidModify" value="0"/>
		<set name="baseHitTimeFactor" value="0.6"/>
		<set name="baseReuseDelay" value="0"/>
		<set name="baseSafeHeight" value="100"/>
		<set name="aggroRange" value="1000"/>
		<set name="shots" value="NONE"/>
		<set name="texture" value=""/>
		<set name="baseDamageRange" value="0;0;80;120"/>
		<equip>
			<rhand item_id="2" />	<!--Long Sword-->
			<lhand item_id="20" />	<!--Buckler-->
		</equip>
		<skills>
			<skill id="4416" level="14"/>	<!--Humans-->
			<skill id="4408" level="1"/>	<!--HP Increase (1x)-->
			<skill id="4409" level="1"/>	<!--MP Increase (1x)-->
			<skill id="4410" level="16"/>	<!--Very Strong P. Atk.-->
			<skill id="4411" level="16"/>	<!--Very Strong M. Atk.-->
			<skill id="4412" level="16"/>	<!--Very Strong P. Def.-->
			<skill id="4413" level="16"/>	<!--Very Strong M. Def.-->
			<skill id="4414" level="2"/>	<!--Standard Type-->
			<skill id="4415" level="3"/>	<!--One-handed Sword-->
			<skill id="4045" level="1"/>	<!--Resist Full Magic Attack-->
		</skills>
	</npc>
</list>